autoload/__init__.py
autoload/_decorators.py
autoload/_imports.py
autoload/_loaders.py
autoload/_metadata.py
autoload_module-3.0.0.dist-info/LICENSE
autoload_module-3.0.0.dist-info/METADATA
autoload_module-3.0.0.dist-info/WHEEL
autoload_module-3.0.0.dist-info/RECORD
