Metadata-Version: 2.1
Name: autoload-module
Version: 3.0.0
Summary: Python Autoload Module
Home-page: https://github.com/hiroki0525/autoload_module
License: MIT
Keywords: python,import,autoload,autoload_module,dynamic import
Author: Hiroki Miyaji
Author-email: nukoprogramming@gmail.com
Maintainer: Hiroki Miyaji
Maintainer-email: nukoprogramming@gmail.com
Requires-Python: >=3.9
Classifier: Development Status :: 1 - Planning
Classifier: Intended Audience :: Developers
Classifier: License :: OSI Approved :: MIT License
Classifier: Programming Language :: Python
Classifier: Programming Language :: Python :: 3
Classifier: Programming Language :: Python :: 3.9
Classifier: Programming Language :: Python :: 3.10
Classifier: Programming Language :: Python :: 3.11
Classifier: Programming Language :: Python :: 3.12
Classifier: Programming Language :: Python :: 3.13
Classifier: Programming Language :: Python :: Implementation :: CPython
Classifier: Programming Language :: Python :: Implementation :: PyPy
Classifier: Topic :: Software Development :: Libraries
Project-URL: Documentation, https://github.com/hiroki0525/autoload_module
Project-URL: Repository, https://github.com/hiroki0525/autoload_module
